ctrl4ai/__init__.py
ctrl4ai/_ordinal_dictionary.py
ctrl4ai/automl.py
ctrl4ai/datadict.py
ctrl4ai/datasets.py
ctrl4ai/exceptions.py
ctrl4ai/helper.py
ctrl4ai/prepdata.py
ctrl4ai-1.0.24.dist-info/LICENSE
ctrl4ai-1.0.24.dist-info/METADATA
ctrl4ai-1.0.24.dist-info/WHEEL
ctrl4ai-1.0.24.dist-info/top_level.txt
ctrl4ai-1.0.24.dist-info/RECORD
