Metadata-Version: 2.1
Name: ctrl4ai
Version: 1.0.24
Summary: A helper package for Machine Learning and Deep Learning Algorithms
Home-page: https://github.com/vkreat-tech/ctrl4ai
Author: Shaji James
Author-email: shajijames7@gmail.com
Classifier: Programming Language :: Python :: 3
Classifier: License :: OSI Approved :: MIT License
Classifier: Operating System :: OS Independent
Classifier: Development Status :: 5 - Production/Stable
Classifier: Topic :: Scientific/Engineering :: Artificial Intelligence
Requires-Python: >=3.6
License-File: LICENSE
